<?xml version="1.0" encoding="utf-8"?><DEFECTS><DEFECT>
    <SFA>
      <FILEPATH>C:\vcpkg\installed\x86-windows\include\json\</FILEPATH>
      <FILENAME>value.h</FILENAME>
      <LINE>576</LINE>
      <COLUMN>7</COLUMN>
    </SFA>
    <DEFECTCODE>26812</DEFECTCODE>
    <DESCRIPTION>The enum type 'Json::CommentPlacement' is unscoped. Prefer 'enum class' over 'enum' (Enum.3).</DESCRIPTION>
    <FUNCTION>Json::Value::setComment</FUNCTION>
    <DECORATED>?setComment@Value@Json@@QAEXPBDW4CommentPlacement@2@@Z</DECORATED>
    <FUNCLINE>576</FUNCLINE>
    <PATH></PATH>
  </DEFECT><DEFECT>
    <SFA>
      <FILEPATH>C:\vcpkg\installed\x86-windows\include\json\</FILEPATH>
      <FILENAME>value.h</FILENAME>
      <LINE>605</LINE>
      <COLUMN>7</COLUMN>
    </SFA>
    <DEFECTCODE>26812</DEFECTCODE>
    <DESCRIPTION>The enum type 'Json::ValueType' is unscoped. Prefer 'enum class' over 'enum' (Enum.3).</DESCRIPTION>
    <FUNCTION>Json::Value::setType</FUNCTION>
    <DECORATED>?setType@Value@Json@@AAEXW4ValueType@2@@Z</DECORATED>
    <FUNCLINE>605</FUNCLINE>
    <PATH></PATH>
  </DEFECT><DEFECT>
    <SFA>
      <FILEPATH>C:\Users\PC-Casa\source\repos\Gasolineras\Gasolineras\</FILEPATH>
      <FILENAME>Source.cpp</FILENAME>
      <LINE>31</LINE>
      <COLUMN>0</COLUMN>
    </SFA>
    <DEFECTCODE>26495</DEFECTCODE>
    <DESCRIPTION>Variable 'tListaGasolineras::registros' is uninitialized. Always initialize a member variable (type.6).</DESCRIPTION>
    <FUNCTION>tListaGasolineras::{ctor}</FUNCTION>
    <DECORATED>??0tListaGasolineras@@QAE@XZ</DECORATED>
    <FUNCLINE>31</FUNCLINE>
    <ADDITIONALINFO>
      <targetSymbol>tListaGasolineras::registros</targetSymbol>
    </ADDITIONALINFO>
    <PATH></PATH>
  </DEFECT><DEFECT>
    <SFA>
      <FILEPATH>C:\Users\PC-Casa\source\repos\Gasolineras\Gasolineras\</FILEPATH>
      <FILENAME>Source.cpp</FILENAME>
      <LINE>119</LINE>
      <COLUMN>13</COLUMN>
    </SFA>
    <DEFECTCODE>26812</DEFECTCODE>
    <DESCRIPTION>The enum type 'CURLcode' is unscoped. Prefer 'enum class' over 'enum' (Enum.3).</DESCRIPTION>
    <FUNCTION>cargarDatosGasolineras</FUNCTION>
    <DECORATED>?cargarDatosGasolineras@@YAXAAUtListaGasolineras@@@Z</DECORATED>
    <FUNCLINE>114</FUNCLINE>
    <PATH></PATH>
  </DEFECT><DEFECT>
    <SFA>
      <FILEPATH>C:\Users\PC-Casa\source\repos\Gasolineras\Gasolineras\</FILEPATH>
      <FILENAME>Source.cpp</FILENAME>
      <LINE>22</LINE>
      <COLUMN>0</COLUMN>
    </SFA>
    <DEFECTCODE>26495</DEFECTCODE>
    <DESCRIPTION>Variable 'tGasolineras::coordenadaY' is uninitialized. Always initialize a member variable (type.6).</DESCRIPTION>
    <FUNCTION>tGasolineras::{ctor}</FUNCTION>
    <DECORATED>??0tGasolineras@@QAE@XZ</DECORATED>
    <FUNCLINE>22</FUNCLINE>
    <ADDITIONALINFO>
      <targetSymbol>tGasolineras::coordenadaY</targetSymbol>
    </ADDITIONALINFO>
    <PATH></PATH>
  </DEFECT><DEFECT>
    <SFA>
      <FILEPATH>C:\Users\PC-Casa\source\repos\Gasolineras\Gasolineras\</FILEPATH>
      <FILENAME>Source.cpp</FILENAME>
      <LINE>193</LINE>
      <COLUMN>35</COLUMN>
    </SFA>
    <DEFECTCODE>6385</DEFECTCODE>
    <DESCRIPTION>Reading invalid data from 'listaAuxiliar.registros':  the readable size is '(unsigned int)*80+4' bytes, but '160' bytes may be read.</DESCRIPTION>
    <FUNCTION>redimensionar</FUNCTION>
    <DECORATED>?redimensionar@@YAXAAUtListaGasolineras@@@Z</DECORATED>
    <FUNCLINE>188</FUNCLINE>
    <PROBABILITY>1</PROBABILITY>
    <RANK>4</RANK>
    <CATEGORY>
      <RULECATEGORY>mspft</RULECATEGORY>
    </CATEGORY>
    <PATH>
      <SFA>
        <FILEPATH>C:\Users\PC-Casa\source\repos\Gasolineras\Gasolineras\</FILEPATH>
        <FILENAME>Source.cpp</FILENAME>
        <LINE>189</LINE>
        <COLUMN>22</COLUMN>
        <KEYEVENT>
          <ID>1</ID>
          <KIND>declaration</KIND>
          <IMPORTANCE>Full</IMPORTANCE>
          <MESSAGE>'listaAuxiliar' receives the Return value from 'tListaGasolineras::{ctor}' (declared on line 31)</MESSAGE>
        </KEYEVENT>
      </SFA>
      <SFA>
        <FILEPATH>C:\Users\PC-Casa\source\repos\Gasolineras\Gasolineras\</FILEPATH>
        <FILENAME>Source.cpp</FILENAME>
        <LINE>189</LINE>
        <COLUMN>22</COLUMN>
        <KEYEVENT>
          <ID>2</ID>
          <KIND>declaration</KIND>
          <IMPORTANCE>Full</IMPORTANCE>
          <MESSAGE>'listaAuxiliar' receives the Return value from 'tListaGasolineras::{ctor}' (declared on line 31)</MESSAGE>
        </KEYEVENT>
      </SFA>
      <SFA>
        <FILEPATH>C:\Users\PC-Casa\source\repos\Gasolineras\Gasolineras\</FILEPATH>
        <FILENAME>Source.cpp</FILENAME>
        <LINE>190</LINE>
        <COLUMN>28</COLUMN>
      </SFA>
      <SFA>
        <FILEPATH>C:\Users\PC-Casa\source\repos\Gasolineras\Gasolineras\</FILEPATH>
        <FILENAME>Source.cpp</FILENAME>
        <LINE>191</LINE>
        <COLUMN>28</COLUMN>
      </SFA>
      <SFA>
        <FILEPATH>C:\Users\PC-Casa\source\repos\Gasolineras\Gasolineras\</FILEPATH>
        <FILENAME>Source.cpp</FILENAME>
        <LINE>192</LINE>
        <COLUMN>13</COLUMN>
      </SFA>
      <SFA>
        <FILEPATH>C:\Users\PC-Casa\source\repos\Gasolineras\Gasolineras\</FILEPATH>
        <FILENAME>Source.cpp</FILENAME>
        <LINE>192</LINE>
        <COLUMN>22</COLUMN>
        <KEYEVENT>
          <ID>3</ID>
          <KIND>branch</KIND>
          <IMPORTANCE>Full</IMPORTANCE>
          <MESSAGE>Enter this loop, (assume 'i&lt;listaGasolineras.DimAct-N')</MESSAGE>
        </KEYEVENT>
      </SFA>
      <SFA>
        <FILEPATH>C:\Users\PC-Casa\source\repos\Gasolineras\Gasolineras\</FILEPATH>
        <FILENAME>Source.cpp</FILENAME>
        <LINE>193</LINE>
        <COLUMN>35</COLUMN>
      </SFA>
      <SFA>
        <FILEPATH>C:\Users\PC-Casa\source\repos\Gasolineras\Gasolineras\</FILEPATH>
        <FILENAME>Source.cpp</FILENAME>
        <LINE>192</LINE>
        <COLUMN>54</COLUMN>
        <KEYEVENT>
          <ID>4</ID>
          <KIND>declaration</KIND>
          <IMPORTANCE>Essential</IMPORTANCE>
          <MESSAGE>'i' may equal 1</MESSAGE>
        </KEYEVENT>
      </SFA>
      <SFA>
        <FILEPATH>C:\Users\PC-Casa\source\repos\Gasolineras\Gasolineras\</FILEPATH>
        <FILENAME>Source.cpp</FILENAME>
        <LINE>192</LINE>
        <COLUMN>22</COLUMN>
        <KEYEVENT>
          <ID>5</ID>
          <KIND>branch</KIND>
          <IMPORTANCE>Full</IMPORTANCE>
          <MESSAGE>Continue this loop, (assume 'i&lt;listaGasolineras.DimAct-N')</MESSAGE>
        </KEYEVENT>
      </SFA>
      <SFA>
        <FILEPATH>C:\Users\PC-Casa\source\repos\Gasolineras\Gasolineras\</FILEPATH>
        <FILENAME>Source.cpp</FILENAME>
        <LINE>193</LINE>
        <COLUMN>35</COLUMN>
        <KEYEVENT>
          <ID>6</ID>
          <KIND>declaration</KIND>
          <IMPORTANCE>Full</IMPORTANCE>
          <MESSAGE>'i' is an Output from 'tGasolineras::=' (declared on line 22)</MESSAGE>
        </KEYEVENT>
      </SFA>
      <SFA>
        <FILEPATH>C:\Users\PC-Casa\source\repos\Gasolineras\Gasolineras\</FILEPATH>
        <FILENAME>Source.cpp</FILENAME>
        <LINE>193</LINE>
        <COLUMN>35</COLUMN>
        <KEYEVENT>
          <ID>7</ID>
          <KIND>usage</KIND>
          <IMPORTANCE>Essential</IMPORTANCE>
          <MESSAGE>Invalid read from 'listaAuxiliar.registros', (outside its readable range)</MESSAGE>
        </KEYEVENT>
      </SFA>
    </PATH>
  </DEFECT><DEFECT>
    <SFA>
      <FILEPATH>C:\Users\PC-Casa\source\repos\Gasolineras\Gasolineras\</FILEPATH>
      <FILENAME>Source.cpp</FILENAME>
      <LINE>243</LINE>
      <COLUMN>5</COLUMN>
    </SFA>
    <DEFECTCODE>6262</DEFECTCODE>
    <DESCRIPTION>Function uses '80028' bytes of stack:  exceeds /analyze:stacksize '16384'.  Consider moving some data to heap.</DESCRIPTION>
    <FUNCTION>merge</FUNCTION>
    <DECORATED>?merge@@YAXAAUtListaGasolineras@@HHH@Z</DECORATED>
    <FUNCLINE>243</FUNCLINE>
    <PATH></PATH>
  </DEFECT></DEFECTS>